flake8_elegant_objects/__init__.py
flake8_elegant_objects/__main__.py
flake8_elegant_objects/base.py
flake8_elegant_objects/no_constructor_code.py
flake8_elegant_objects/no_er_name.py
flake8_elegant_objects/no_getters_setters.py
flake8_elegant_objects/no_implementation_inheritance.py
flake8_elegant_objects/no_impure_tests.py
flake8_elegant_objects/no_null.py
flake8_elegant_objects/no_orm.py
flake8_elegant_objects/no_public_methods_without_contracts.py
flake8_elegant_objects/no_static.py
flake8_elegant_objects/no_type_discrimination.py
flake8_elegant_objects/no_mutable_objects/__init__.py
flake8_elegant_objects/no_mutable_objects/base.py
flake8_elegant_objects/no_mutable_objects/contract_checker.py
flake8_elegant_objects/no_mutable_objects/copy_on_write_checker.py
flake8_elegant_objects/no_mutable_objects/core.py
flake8_elegant_objects/no_mutable_objects/deep_checker.py
flake8_elegant_objects/no_mutable_objects/factory_checker.py
flake8_elegant_objects/no_mutable_objects/pattern_detectors.py
flake8_elegant_objects/no_mutable_objects/shared_state_checker.py
flake8_elegant_objects-1.1.1.dist-info/METADATA
flake8_elegant_objects-1.1.1.dist-info/WHEEL
flake8_elegant_objects-1.1.1.dist-info/entry_points.txt
flake8_elegant_objects-1.1.1.dist-info/licenses/LICENSE
flake8_elegant_objects-1.1.1.dist-info/RECORD
