Metadata-Version: 2.4
Name: flake8-elegant-objects
Version: 1.1.1
Summary: Flake8 plugin enforcing Elegant Objects principles: no -er naming, no null, no getters/setters, immutable objects
Project-URL: Homepage, https://github.com/AntonProkopyev/flake8-elegant-objects
Project-URL: Repository, https://github.com/AntonProkopyev/flake8-elegant-objects.git
Project-URL: Issues, https://github.com/AntonProkopyev/flake8-elegant-objects/issues
Project-URL: Documentation, https://github.com/AntonProkopyev/flake8-elegant-objects#readme
Author: Anton Prokopyev
License: MIT
License-File: LICENSE
Keywords: code-quality,elegant-objects,flake8,linting,object-oriented,python,static-analysis
Classifier: Development Status :: 4 - Beta
Classifier: Environment :: Console
Classifier: Framework :: Flake8
Classifier: Intended Audience :: Developers
Classifier: License :: OSI Approved :: MIT License
Classifier: Operating System :: OS Independent
Classifier: Programming Language :: Python
Classifier: Programming Language :: Python :: 3
Classifier: Programming Language :: Python :: 3.10
Classifier: Programming Language :: Python :: 3.11
Classifier: Programming Language :: Python :: 3.12
Classifier: Programming Language :: Python :: 3.13
Classifier: Topic :: Software Development :: Libraries :: Python Modules
Classifier: Topic :: Software Development :: Quality Assurance
Classifier: Typing :: Typed
Requires-Python: >=3.10
